setup.py
src/xmlrpcauth/__init__.py
src/xmlrpcauth/tests.py
src/xmlrpcauth.egg-info/PKG-INFO
src/xmlrpcauth.egg-info/SOURCES.txt
src/xmlrpcauth.egg-info/dependency_links.txt
src/xmlrpcauth.egg-info/not-zip-safe
src/xmlrpcauth.egg-info/top_level.txt