Metadata-Version: 1.0
Name: xmlrpcauth
Version: 1.1
Summary: HTTP Basic-Auth transport for xmlrpclib.Server
